{
  "defaultSearchEngine": "duckduckgo",
  "customSearchEngine": [
    {
      "name": "duckduckgo",
      "url": "https://duckduckgo.com/?q="
    }
  ],
  "ignoreList": [
    "notion",
    "craft"
  ],
  "alwaysShowCustomSearch": false,
  "showOtherSearchEngines": false,
  "showSearchBarInPage": true,
  "markdownPath": "/Extras/Web Pages",
  "customHighlightFormat": false,
  "highlightFormat": "[{CONTENT}]({URL})",
  "highlightInSameTab": false,
  "openInSameTab": true,
  "showRefreshButton": true,
  "openInObsidianWeb": true,
  "useCustomIcons": false,
  "useWebview": false,
  "useIconList": true,
  "darkMode": true,
  "bookmarkManager": {
    "openBookMark": false,
    "saveBookMark": false,
    "sendToReadWise": false,
    "pagination": "12",
    "category": "- Computer\n    - 算法\n    - 数据结构\n- obsidian\n    - surfing\n    - dataview\n",
    "defaultCategory": "ROOT",
    "defaultColumnList": [
      "name",
      "description",
      "url",
      "category",
      "tags",
      "created",
      "modified",
      "action"
    ],
    "defaultFilterType": "tree"
  },
  "treeData": [
    {
      "id": "a81edba30189500f",
      "parent": 0,
      "droppable": true,
      "text": "Nix language basics — nix.dev documentation",
      "data": {
        "fileType": "site",
        "fileSize": "",
        "icon": {}
      }
    }
  ]
}